{
  "jogadores": {
    "tiala": {
      "password": "123456",
      "progresso": {},
      "score": 0
    },
    "tiii": {
      "password": "12347",
      "progresso": {
        "player": {
          "x": 1,
          "y": 7
        },
        "objects": {
          "2,1": "ammo",
          "5,5": "ammo",
          "0,1": "enemy",
          "1,1": "ammo",
          "2,7": "enemy",
          "1,8": "med"
        },
        "visited": {
          "1,1": true,
          "2,2": true,
          "3,3": true,
          "2,3": true,
          "1,3": true,
          "2,4": true,
          "3,5": true,
          "4,6": true,
          "4,5": true,
          "4,4": true,
          "4,3": true,
          "3,2": true,
          "0,2": true,
          "0,3": true,
          "1,4": true,
          "1,5": true,
          "1,6": true,
          "1,7": true
        },
        "health": 0,
        "steps": 21,
        "difficulty": 0.31,
        "gameState": "lose",
        "ammo": 0,
        "monstersKilled": 12
      },
      "score": 21,
      "monstersKilled": 12
    },
    "elle": {
      "password": "147258",
      "progresso": {},
      "score": 0
    },
    "oii": {
      "password": "123456",
      "progresso": {},
      "score": 0
    },
    "mk": {
      "password": "123456",
      "progresso": {
        "player": {
          "x": 0,
          "y": 0
        },
        "objects": {},
        "visited": {},
        "health": 3,
        "steps": 0,
        "difficulty": 0.1,
        "gameState": "playing",
        "ammo": 5,
        "monstersKilled": 0
      },
      "score": 11,
      "monstersKilled": 3
    }
  },
  "rankings": [
    {
      "username": "tiii",
      "score": 21,
      "monstersKilled": 12
    },
    {
      "username": "mk",
      "score": 11,
      "monstersKilled": 3
    }
  ]
}